{
  "province": "xizang",
  "name": "иҘҝи—ҸиҮӘжІ»еҢә",
  "verified_count": 3,
  "account_start": {
    "year": 2005,
    "month": 7
  },
  "viewing_start": {
    "year": 2005,
    "month": 7
  },
  "base_rates": {
    "prov": {
      "1978": 1224,
      "1979": 1285,
      "1980": 1349,
      "1981": 1417,
      "1982": 1488,
      "1983": 1562,
      "1984": 1640,
      "1985": 1722,
      "1986": 1808,
      "1987": 1899,
      "1988": 1994,
      "1989": 2093,
      "1990": 2198,
      "1991": 2308,
      "1992": 2423,
      "1993": 2544,
      "1994": 2671,
      "1995": 2805,
      "1996": 2945,
      "1997": 3093,
      "1998": 3247,
      "1999": 3410,
      "2000": 3580,
      "2001": 3759,
      "2002": 3947,
      "2003": 4144,
      "2004": 4352,
      "2005": 1550,
      "2006": 2300,
      "2007": 2500,
      "2008": 2800,
      "2009": 2900,
      "2010": 3000,
      "2011": 3200,
      "2012": 3500,
      "2013": 3600,
      "2014": 4000,
      "2015": 5100,
      "2016": 5929,
      "2017": 6708,
      "2018": 7587,
      "2019": 7815,
      "2020": 8143,
      "2021": 8839,
      "2022": 9900,
      "2023": 10791,
      "2024": 11546,
      "2025": 11777
    }
  },
  "avg_salary_history": {
    "1998": 915.58,
    "1999": 1080.17,
    "2000": 1248,
    "2001": 1595.33,
    "2002": 2063.83,
    "2003": 2244.25,
    "2004": 2572.75,
    "2005": 1550,
    "2006": 2300,
    "2007": 2500,
    "2008": 2800,
    "2009": 2900,
    "2010": 3000,
    "2011": 3200,
    "2012": 3500,
    "2013": 3600,
    "2014": 4000,
    "2015": 5100,
    "2016": 5929,
    "2017": 6708,
    "2018": 7587,
    "2019": 7815,
    "2020": 8143,
    "2021": 8839,
    "2022": 9900,
    "2023": 10791,
    "2024": 11777,
    "2025": 11777
  },
  "flex_retire": {
    "male": 55,
    "female": 45
  },
  "min_years": {
    "2025": 15,
    "2026": 15,
    "2027": 15,
    "2028": 15,
    "2029": 15,
    "2030": 15.5,
    "2031": 16,
    "2032": 16.5,
    "2033": 17,
    "2034": 17.5,
    "2035": 18,
    "2036": 18.5,
    "2037": 19,
    "2038": 19.5,
    "2039": 20,
    "2040": 20,
    "2041": 20,
    "2042": 20,
    "2043": 20,
    "2044": 20,
    "2045": 20
  },
  "delay_retirement": {
    "effective_date": "2026-01-01",
    "male": {
      "base_year": 1965,
      "step": 4,
      "cap_months": 36
    },
    "fc": {
      "base_year": 1970,
      "step": 4,
      "cap_months": 36
    },
    "fw55": {
      "base_year": 1975,
      "step": 2,
      "cap_months": 60
    }
  },
  "modules": {
    "basic_pension": {
      "enabled": true,
      "rate_per_year": 0.01,
      "formula": "(и®ЎеҸ‘еҹәж•°+жҢҮж•°еҢ–жңҲеқҮ)/2Г—е№ҙйҷҗГ—1%"
    },
    "extra_pension": {
      "enabled": false
    },
    "personal_account": {
      "enabled": true
    },
    "transitional_pension": {
      "enabled": true,
      "coefficient": 0.014,
      "notes": "и—Ҹж”ҝеҸ‘гҖ”2006гҖ•37еҸ·гҖӮиҝҮжёЎзі»ж•°1.4%гҖӮе»әиҙҰ~2005-07гҖӮе…¬ејҸ=жҢҮж•°еҢ–е·Ҙиө„Г—и§ҶеҗҢе№ҙйҷҗГ—1.4%гҖӮ"
    },
    "special_addition": {
      "enabled": true,
      "type": "plateau",
      "notes": "и—Ҹж”ҝеҸ‘гҖ”2006гҖ•37еҸ·гҖҒи—ҸеҠізӨҫеҠһгҖ”2007гҖ•6еҸ·гҖӮй«ҳеҺҹиЎҘиҙҙ=жҢҮж•°еҢ–жңҲеқҮГ—жҜ”дҫӢ(10е№ҙ5%/15е№ҙ10%/20е№ҙ15%)+дәӨйҖҡиҙ№30+еҸ–жҡ–иҙ№39.88+зҰҸеҲ©йҮ‘260гҖӮ"
    }
  },
  "cities": [
    {
      "code": "prov",
      "name": "е…ЁзңҒй»ҳи®Ө"
    }
  ],
  "notes": {
    "policy": "и—Ҹж”ҝеҸ‘гҖ”2006гҖ•37еҸ· + и—ҸеҠізӨҫеҠһгҖ”2007гҖ•6еҸ·гҖӮиҝҮжёЎ1.4%гҖӮй«ҳеҺҹиЎҘиҙҙеҲҶж®өжҜ”дҫӢгҖӮзҒөжҙ»е°ұдёҡеҘі45/з”·55йҖҖдј‘гҖӮеҹәзЎҖз”ЁдёҠе№ҙеәҰзӨҫе№ігҖӮе»әиҙҰзәҰ2005е№ҙпјҲжһҒжҷҡпјүгҖӮи®ЎеҸ‘еҹәж•°вүҲзӨҫе№іпјҲ2025=11777е…ЁеӣҪз¬¬дәҢпјүгҖӮ",
    "data_source": "е®ҳж–№ж•°жҚ®"
  }
}